aiohttp_prometheus/__init__.py
aiohttp_prometheus/middleware.py
aiohttp_prometheus/view.py
aiohttp_prometheus-0.1.0.dist-info/LICENSE
aiohttp_prometheus-0.1.0.dist-info/METADATA
aiohttp_prometheus-0.1.0.dist-info/WHEEL
aiohttp_prometheus-0.1.0.dist-info/top_level.txt
aiohttp_prometheus-0.1.0.dist-info/RECORD
