Metadata-Version: 2.1
Name: aiohttp-prometheus
Version: 0.1.0
Summary: HTTP metrics for a aiohttp application
Home-page: https://github.com/globocom/aiohttp-prometheus
Author: Globo.com
Author-email: backstage@corp.globo.com
License: MIT
Keywords: prometheus aiohttp
Platform: UNKNOWN
Classifier: Development Status :: 4 - Beta
Classifier: Intended Audience :: Developers
Classifier: License :: OSI Approved :: MIT License
Classifier: Natural Language :: English
Classifier: Operating System :: MacOS
Classifier: Operating System :: POSIX
Classifier: Operating System :: Unix
Classifier: Operating System :: OS Independent
Classifier: Programming Language :: Python :: 2.7
Classifier: Programming Language :: Python :: 3.5
Requires-Dist: aiohttp
Requires-Dist: prometheus-client (==0.7.1)
Provides-Extra: tests
Requires-Dist: pytest (==5.2.2) ; extra == 'tests'
Requires-Dist: pytest-aiohttp (==0.3.0) ; extra == 'tests'
Requires-Dist: nose ; extra == 'tests'
Requires-Dist: coverage ; extra == 'tests'
Requires-Dist: flake8 ; extra == 'tests'
